{
  "welds": [
    {
      "start": {
        "xyz": [
          25.98929819504827,
          -115.59711317108565,
          5.0
        ],
        "pose": [
          0.47550691611104845,
          -0.6637468187473496,
          0.5773502691896257
        ]
      },
      "end": {
        "xyz": [
          15.596774921305995,
          -113.87994735513345,
          5.0
        ],
        "pose": [
          -0.6637468187473496,
          -0.47550691611104845,
          0.5773502691896257
        ]
      }
    },
    {
      "start": {
        "xyz": [
          15.596774921305995,
          -113.87994735513345,
          5.0
        ],
        "pose": [
          -0.6637468187473496,
          -0.47550691611104845,
          0.5773502691896257
        ]
      },
      "end": {
        "xyz": [
          55.03182343133134,
          124.78638040154814,
          5.0
        ],
        "pose": [
          -0.47550691611104845,
          0.6637468187473496,
          0.5773502691896257
        ]
      }
    },
    {
      "start": {
        "xyz": [
          55.03182343133134,
          124.78638040154814,
          5.0
        ],
        "pose": [
          -0.47550691611104845,
          0.6637468187473496,
          0.5773502691896257
        ]
      },
      "end": {
        "xyz": [
          65.42434670517,
          123.06921458558,
          5.0
        ],
        "pose": [
          0.6637468187473496,
          0.47550691611104845,
          0.5773502691896257
        ]
      }
    },
    {
      "start": {
        "xyz": [
          65.42434670517,
          123.06921458558,
          5.0
        ],
        "pose": [
          0.6637468187473496,
          0.47550691611104845,
          0.5773502691896257
        ]
      },
      "end": {
        "xyz": [
          25.98929819504827,
          -115.59711317108565,
          5.0
        ],
        "pose": [
          0.47550691611104845,
          -0.6637468187473496,
          0.5773502691896257
        ]
      }
    },
    {
      "start": {
        "xyz": [
          -80.10110059307968,
          -108.3539591956885,
          5.0
        ],
        "pose": [
          0.47550691611104845,
          -0.6637468187473496,
          0.5773502691896257
        ]
      },
      "end": {
        "xyz": [
          -95.72697220665593,
          -105.77208260301484,
          5.0
        ],
        "pose": [
          -0.6637468187473496,
          -0.47550691611104845,
          0.5773502691896257
        ]
      }
    },
    {
      "start": {
        "xyz": [
          -95.72697220665593,
          -105.77208260301484,
          5.0
        ],
        "pose": [
          -0.6637468187473496,
          -0.47550691611104845,
          0.5773502691896257
        ]
      },
      "end": {
        "xyz": [
          -65.11485878413906,
          79.49663067282269,
          5.0
        ],
        "pose": [
          -0.47550691611104845,
          0.6637468187473496,
          0.5773502691896257
        ]
      }
    },
    {
      "start": {
        "xyz": [
          -65.11485878413906,
          79.49663067282269,
          5.0
        ],
        "pose": [
          -0.47550691611104845,
          0.6637468187473496,
          0.5773502691896257
        ]
      },
      "end": {
        "xyz": [
          -49.48898717049,
          76.914754080137,
          5.0
        ],
        "pose": [
          0.6637468187473496,
          0.47550691611104845,
          0.5773502691896257
        ]
      }
    },
    {
      "start": {
        "xyz": [
          -49.48898717049,
          76.914754080137,
          5.0
        ],
        "pose": [
          0.6637468187473496,
          0.47550691611104845,
          0.5773502691896257
        ]
      },
      "end": {
        "xyz": [
          -80.10110059307968,
          -108.3539591956885,
          5.0
        ],
        "pose": [
          0.47550691611104845,
          -0.6637468187473496,
          0.5773502691896257
        ]
      }
    }
  ]
}